[{"company":"Meetz","position":"Staff Scientist","jobStatus":"interview","jobType":"part-time","jobLocation":"Yangxu","createdAt":"2024-01-30T05:43:24Z"},
{"company":"Tekfly","position":"Software Consultant","jobStatus":"pending","jobType":"part-time","jobLocation":"Long Layu","createdAt":"2023-12-05T11:57:34Z"},
{"company":"Livepath","position":"Actuary","jobStatus":"declined","jobType":"internship","jobLocation":"Zheleznogorsk","createdAt":"2023-09-07T13:31:20Z"},
{"company":"Kwinu","position":"Senior Editor","jobStatus":"pending","jobType":"full-time","jobLocation":"Estrada","createdAt":"2024-03-14T22:17:03Z"},
{"company":"Yozio","position":"Environmental Specialist","jobStatus":"interview","jobType":"full-time","jobLocation":"Pojok","createdAt":"2024-01-08T18:02:24Z"},
{"company":"Midel","position":"Design Engineer","jobStatus":"interview","jobType":"internship","jobLocation":"Pilot Butte","createdAt":"2023-12-23T05:10:13Z"},
{"company":"Blogtag","position":"Pharmacist","jobStatus":"declined","jobType":"part-time","jobLocation":"Candating","createdAt":"2023-07-20T11:40:45Z"},
{"company":"Yodoo","position":"Analog Circuit Design manager","jobStatus":"interview","jobType":"part-time","jobLocation":"Sungaikakap","createdAt":"2024-02-14T15:21:23Z"},
{"company":"Dabshots","position":"Programmer I","jobStatus":"declined","jobType":"full-time","jobLocation":"Xikou","createdAt":"2023-09-03T14:23:33Z"},
{"company":"Twitterbeat","position":"Sales Representative","jobStatus":"pending","jobType":"internship","jobLocation":"Zemun","createdAt":"2023-12-09T22:15:55Z"},
{"company":"Jabbertype","position":"Cost Accountant","jobStatus":"interview","jobType":"part-time","jobLocation":"Formosa","createdAt":"2023-11-18T09:24:05Z"},
{"company":"Tazz","position":"Senior Quality Engineer","jobStatus":"interview","jobType":"full-time","jobLocation":"Tembol","createdAt":"2023-07-14T02:24:14Z"},
{"company":"Gigashots","position":"Registered Nurse","jobStatus":"interview","jobType":"part-time","jobLocation":"Rotterdam postbusnummers","createdAt":"2023-04-10T22:18:21Z"},
{"company":"Blognation","position":"Internal Auditor","jobStatus":"pending","jobType":"internship","jobLocation":"Lagoa Santa","createdAt":"2023-05-15T23:51:12Z"},
{"company":"Quamba","position":"Financial Advisor","jobStatus":"declined","jobType":"part-time","jobLocation":"Komarno","createdAt":"2023-06-02T04:57:24Z"},
{"company":"Yabox","position":"Analog Circuit Design manager","jobStatus":"interview","jobType":"internship","jobLocation":"Matlang","createdAt":"2023-06-16T17:24:30Z"},
{"company":"Oodoo","position":"Chemical Engineer","jobStatus":"interview","jobType":"full-time","jobLocation":"Ungheni","createdAt":"2023-09-04T03:59:44Z"},
{"company":"Flipstorm","position":"Chief Design Engineer","jobStatus":"declined","jobType":"part-time","jobLocation":"Jintan","createdAt":"2023-09-08T15:07:19Z"},
{"company":"Cogilith","position":"Cost Accountant","jobStatus":"interview","jobType":"full-time","jobLocation":"Tianjiazhuang","createdAt":"2024-02-14T10:49:45Z"},
{"company":"Roomm","position":"Research Assistant IV","jobStatus":"interview","jobType":"part-time","jobLocation":"Lavrica","createdAt":"2024-03-04T18:04:16Z"},
{"company":"Meembee","position":"Teacher","jobStatus":"interview","jobType":"full-time","jobLocation":"Tangshan","createdAt":"2023-07-20T15:32:37Z"},
{"company":"Quimba","position":"Programmer III","jobStatus":"pending","jobType":"part-time","jobLocation":"Niedźwiada","createdAt":"2024-01-27T10:16:20Z"},
{"company":"Skipfire","position":"Web Developer II","jobStatus":"pending","jobType":"part-time","jobLocation":"Morioka-shi","createdAt":"2023-04-17T17:10:51Z"},
{"company":"Rhybox","position":"Statistician IV","jobStatus":"interview","jobType":"part-time","jobLocation":"Torino","createdAt":"2023-05-31T21:17:46Z"},
{"company":"Feedfish","position":"Recruiting Manager","jobStatus":"declined","jobType":"internship","jobLocation":"La Condamine","createdAt":"2023-04-15T01:37:37Z"},
{"company":"Bubbletube","position":"Pharmacist","jobStatus":"interview","jobType":"full-time","jobLocation":"Zhuangbu","createdAt":"2023-04-09T09:58:24Z"},
{"company":"Eamia","position":"Programmer II","jobStatus":"interview","jobType":"full-time","jobLocation":"Zhouzhuang","createdAt":"2023-10-02T06:41:01Z"},
{"company":"Jabberbean","position":"Structural Analysis Engineer","jobStatus":"pending","jobType":"internship","jobLocation":"Poljčane","createdAt":"2023-09-12T19:52:20Z"},
{"company":"Photobean","position":"Account Coordinator","jobStatus":"interview","jobType":"part-time","jobLocation":"Huangnaihai","createdAt":"2023-08-31T06:42:05Z"},
{"company":"Zazio","position":"Food Chemist","jobStatus":"pending","jobType":"part-time","jobLocation":"Tombatu","createdAt":"2024-03-13T01:42:39Z"},
{"company":"Thoughtblab","position":"Programmer Analyst II","jobStatus":"declined","jobType":"part-time","jobLocation":"Lenghu","createdAt":"2023-12-31T06:04:27Z"},
{"company":"Rhycero","position":"Analog Circuit Design manager","jobStatus":"pending","jobType":"internship","jobLocation":"Tambovka","createdAt":"2023-07-12T00:09:56Z"},
{"company":"Realcube","position":"Senior Sales Associate","jobStatus":"pending","jobType":"internship","jobLocation":"Campo","createdAt":"2023-08-24T18:21:22Z"},
{"company":"Edgeblab","position":"Environmental Tech","jobStatus":"pending","jobType":"internship","jobLocation":"Shiqiao","createdAt":"2023-10-02T00:02:22Z"},
{"company":"Kwideo","position":"VP Quality Control","jobStatus":"interview","jobType":"part-time","jobLocation":"La Reforma","createdAt":"2023-09-14T11:54:11Z"},
{"company":"Rhynoodle","position":"Staff Accountant III","jobStatus":"pending","jobType":"internship","jobLocation":"Dayang","createdAt":"2023-09-09T23:25:25Z"},
{"company":"Gabvine","position":"Recruiter","jobStatus":"interview","jobType":"part-time","jobLocation":"La Libertad","createdAt":"2024-02-25T11:29:54Z"},
{"company":"Yodoo","position":"Business Systems Development Analyst","jobStatus":"interview","jobType":"internship","jobLocation":"Shangma","createdAt":"2023-08-25T14:35:36Z"},
{"company":"Avaveo","position":"Research Nurse","jobStatus":"declined","jobType":"part-time","jobLocation":"Xinxu","createdAt":"2024-01-29T19:02:04Z"},
{"company":"Agivu","position":"Sales Associate","jobStatus":"interview","jobType":"full-time","jobLocation":"Shuangyuan","createdAt":"2023-03-29T11:29:35Z"},
{"company":"Topicblab","position":"Operator","jobStatus":"pending","jobType":"full-time","jobLocation":"Pochayiv","createdAt":"2023-12-23T18:00:35Z"},
{"company":"Abata","position":"Marketing Manager","jobStatus":"declined","jobType":"internship","jobLocation":"Manika","createdAt":"2023-12-30T19:52:14Z"},
{"company":"Riffwire","position":"Desktop Support Technician","jobStatus":"pending","jobType":"internship","jobLocation":"Olleros","createdAt":"2023-04-15T16:53:43Z"},
{"company":"Buzzdog","position":"Financial Analyst","jobStatus":"declined","jobType":"part-time","jobLocation":"Ta`ū","createdAt":"2023-07-17T17:09:32Z"},
{"company":"Twimm","position":"Senior Editor","jobStatus":"pending","jobType":"part-time","jobLocation":"Marseille","createdAt":"2023-10-24T19:07:18Z"},
{"company":"Realbuzz","position":"Senior Developer","jobStatus":"declined","jobType":"part-time","jobLocation":"Klang","createdAt":"2024-02-04T20:55:34Z"},
{"company":"Skipfire","position":"Assistant Professor","jobStatus":"declined","jobType":"part-time","jobLocation":"Fort Portal","createdAt":"2023-05-31T08:42:00Z"},
{"company":"Gabspot","position":"Nurse Practicioner","jobStatus":"interview","jobType":"part-time","jobLocation":"La Mohammedia","createdAt":"2023-04-09T03:12:50Z"},
{"company":"Shuffletag","position":"Business Systems Development Analyst","jobStatus":"declined","jobType":"full-time","jobLocation":"Ryazanskiy","createdAt":"2023-08-10T08:32:06Z"},
{"company":"Divape","position":"Developer I","jobStatus":"declined","jobType":"internship","jobLocation":"Lankaran","createdAt":"2023-06-08T22:32:31Z"},
{"company":"Skippad","position":"Business Systems Development Analyst","jobStatus":"interview","jobType":"part-time","jobLocation":"Novalja","createdAt":"2023-08-31T18:15:33Z"},
{"company":"Skidoo","position":"Computer Systems Analyst IV","jobStatus":"declined","jobType":"full-time","jobLocation":"Rožaje","createdAt":"2023-03-29T02:19:53Z"},
{"company":"Buzzbean","position":"Paralegal","jobStatus":"declined","jobType":"internship","jobLocation":"Loakulu","createdAt":"2023-09-06T15:29:59Z"},
{"company":"Rhynoodle","position":"Office Assistant III","jobStatus":"declined","jobType":"internship","jobLocation":"Kajar","createdAt":"2023-03-25T14:05:42Z"},
{"company":"Tazzy","position":"Sales Representative","jobStatus":"declined","jobType":"part-time","jobLocation":"Rāmganj","createdAt":"2023-11-24T13:16:13Z"},
{"company":"Podcat","position":"Information Systems Manager","jobStatus":"pending","jobType":"full-time","jobLocation":"Uzhhorod","createdAt":"2023-09-01T17:41:33Z"},
{"company":"Twitterlist","position":"Operator","jobStatus":"interview","jobType":"internship","jobLocation":"Sukawening","createdAt":"2023-07-28T08:22:01Z"},
{"company":"Meevee","position":"Environmental Specialist","jobStatus":"declined","jobType":"full-time","jobLocation":"Hokor","createdAt":"2023-09-14T02:41:50Z"},
{"company":"Zava","position":"Pharmacist","jobStatus":"pending","jobType":"internship","jobLocation":"Yamagata-shi","createdAt":"2023-06-12T09:22:12Z"},
{"company":"Nlounge","position":"Nuclear Power Engineer","jobStatus":"declined","jobType":"full-time","jobLocation":"Serdobsk","createdAt":"2023-08-08T06:11:59Z"},
{"company":"Dabjam","position":"Junior Executive","jobStatus":"pending","jobType":"part-time","jobLocation":"Verkhniye Osel’ki","createdAt":"2023-12-16T09:09:00Z"},
{"company":"Devpoint","position":"Editor","jobStatus":"pending","jobType":"part-time","jobLocation":"Jiangyin","createdAt":"2023-03-23T02:22:13Z"},
{"company":"Photospace","position":"Paralegal","jobStatus":"declined","jobType":"part-time","jobLocation":"Suicheng","createdAt":"2024-03-05T11:11:51Z"},
{"company":"Mudo","position":"Design Engineer","jobStatus":"interview","jobType":"part-time","jobLocation":"Ell","createdAt":"2023-07-07T13:54:02Z"},
{"company":"Twimbo","position":"Senior Quality Engineer","jobStatus":"pending","jobType":"full-time","jobLocation":"Seara","createdAt":"2023-12-03T07:00:09Z"},
{"company":"Eayo","position":"Nurse","jobStatus":"declined","jobType":"internship","jobLocation":"Sernur","createdAt":"2023-09-19T20:02:35Z"},
{"company":"Gigabox","position":"Nurse","jobStatus":"pending","jobType":"full-time","jobLocation":"Wenceslao Escalante","createdAt":"2023-09-26T10:32:15Z"},
{"company":"Trupe","position":"Financial Advisor","jobStatus":"interview","jobType":"full-time","jobLocation":"Biao","createdAt":"2023-06-09T13:42:51Z"},
{"company":"Centidel","position":"Software Consultant","jobStatus":"interview","jobType":"part-time","jobLocation":"Sérvia","createdAt":"2023-06-13T15:05:41Z"},
{"company":"Yakitri","position":"Structural Analysis Engineer","jobStatus":"interview","jobType":"internship","jobLocation":"Kiffa","createdAt":"2023-03-26T12:21:54Z"},
{"company":"Flashdog","position":"Geologist III","jobStatus":"declined","jobType":"part-time","jobLocation":"Bojongloa","createdAt":"2024-03-10T05:36:29Z"},
{"company":"Edgewire","position":"Occupational Therapist","jobStatus":"declined","jobType":"full-time","jobLocation":"Arras","createdAt":"2023-08-27T08:20:28Z"},
{"company":"Linktype","position":"Structural Analysis Engineer","jobStatus":"declined","jobType":"part-time","jobLocation":"Puor","createdAt":"2024-02-02T22:09:26Z"},
{"company":"Yoveo","position":"Food Chemist","jobStatus":"pending","jobType":"internship","jobLocation":"Jixiang","createdAt":"2023-12-03T07:07:56Z"},
{"company":"Bubbletube","position":"Senior Sales Associate","jobStatus":"pending","jobType":"full-time","jobLocation":"Wang’er","createdAt":"2023-07-27T07:14:53Z"},
{"company":"Katz","position":"Account Executive","jobStatus":"declined","jobType":"part-time","jobLocation":"Vitry-sur-Seine","createdAt":"2024-01-08T23:44:39Z"},
{"company":"Realblab","position":"Senior Sales Associate","jobStatus":"declined","jobType":"full-time","jobLocation":"Susapaya","createdAt":"2023-08-21T13:45:31Z"},
{"company":"Wordtune","position":"Engineer III","jobStatus":"pending","jobType":"part-time","jobLocation":"Longvic","createdAt":"2023-07-08T02:15:07Z"},
{"company":"Tagtune","position":"Desktop Support Technician","jobStatus":"declined","jobType":"part-time","jobLocation":"Dunyāpur","createdAt":"2024-01-17T13:14:56Z"},
{"company":"Avamba","position":"Research Assistant IV","jobStatus":"interview","jobType":"part-time","jobLocation":"Tsukawaki","createdAt":"2024-02-16T07:38:11Z"},
{"company":"Gabtune","position":"Project Manager","jobStatus":"declined","jobType":"internship","jobLocation":"Erechim","createdAt":"2024-02-08T03:56:58Z"},
{"company":"Viva","position":"Cost Accountant","jobStatus":"declined","jobType":"full-time","jobLocation":"Lam Sonthi","createdAt":"2023-04-18T10:18:56Z"},
{"company":"Twitterworks","position":"Design Engineer","jobStatus":"pending","jobType":"full-time","jobLocation":"Moog","createdAt":"2023-07-17T06:29:26Z"},
{"company":"Kwilith","position":"Human Resources Assistant I","jobStatus":"declined","jobType":"part-time","jobLocation":"Terter","createdAt":"2023-06-07T07:33:34Z"},
{"company":"Photobug","position":"Account Executive","jobStatus":"interview","jobType":"internship","jobLocation":"Örbyhus","createdAt":"2023-05-21T13:54:53Z"},
{"company":"Photobug","position":"Staff Accountant III","jobStatus":"pending","jobType":"part-time","jobLocation":"Owando","createdAt":"2024-02-15T18:48:01Z"},
{"company":"Roodel","position":"Actuary","jobStatus":"declined","jobType":"part-time","jobLocation":"Cuogang","createdAt":"2023-04-08T21:47:00Z"},
{"company":"Voomm","position":"Civil Engineer","jobStatus":"pending","jobType":"part-time","jobLocation":"Huangcaotuo","createdAt":"2023-11-12T05:09:34Z"},
{"company":"Yakitri","position":"Sales Associate","jobStatus":"declined","jobType":"part-time","jobLocation":"Konary","createdAt":"2023-08-14T03:08:23Z"},
{"company":"Blogtags","position":"Account Coordinator","jobStatus":"declined","jobType":"part-time","jobLocation":"Gombangan","createdAt":"2024-02-24T08:25:04Z"},
{"company":"Npath","position":"Business Systems Development Analyst","jobStatus":"pending","jobType":"part-time","jobLocation":"Yukhnov","createdAt":"2024-02-18T10:35:45Z"},
{"company":"Kanoodle","position":"Professor","jobStatus":"interview","jobType":"full-time","jobLocation":"Chrastava","createdAt":"2023-04-30T02:19:33Z"},
{"company":"Yata","position":"Internal Auditor","jobStatus":"declined","jobType":"part-time","jobLocation":"Kalininaul","createdAt":"2024-01-07T15:26:00Z"},
{"company":"Skibox","position":"VP Quality Control","jobStatus":"interview","jobType":"part-time","jobLocation":"Karangsari","createdAt":"2023-05-23T18:24:05Z"},
{"company":"Talane","position":"Marketing Assistant","jobStatus":"interview","jobType":"internship","jobLocation":"Picton","createdAt":"2023-10-27T04:04:32Z"},
{"company":"Browsecat","position":"General Manager","jobStatus":"declined","jobType":"part-time","jobLocation":"Babakankiray","createdAt":"2023-09-13T18:43:06Z"},
{"company":"Flashdog","position":"Food Chemist","jobStatus":"pending","jobType":"full-time","jobLocation":"Yuanqian","createdAt":"2023-04-26T15:28:19Z"},
{"company":"Yakijo","position":"Developer IV","jobStatus":"interview","jobType":"part-time","jobLocation":"Niemodlin","createdAt":"2024-01-16T07:18:22Z"},
{"company":"Edgeblab","position":"Sales Representative","jobStatus":"interview","jobType":"part-time","jobLocation":"Ergong","createdAt":"2023-12-08T16:05:44Z"},
{"company":"Riffwire","position":"Product Engineer","jobStatus":"interview","jobType":"part-time","jobLocation":"Kholm","createdAt":"2023-03-16T02:36:50Z"}]